ansible_autoprovisioner/__init__.py
ansible_autoprovisioner/config.py
ansible_autoprovisioner/daemon.py
ansible_autoprovisioner/executor.py
ansible_autoprovisioner/main.py
ansible_autoprovisioner/matcher.py
ansible_autoprovisioner/state.py
ansible_autoprovisioner/detectors/__init__.py
ansible_autoprovisioner/detectors/aws.py
ansible_autoprovisioner/detectors/base.py
ansible_autoprovisioner/detectors/manager.py
ansible_autoprovisioner/detectors/registry.py
ansible_autoprovisioner/detectors/static.py
ansible_autoprovisioner/notifications/__init__.py
ansible_autoprovisioner/notifications/base.py
ansible_autoprovisioner/notifications/notifier.py
ansible_autoprovisioner/notifications/registry.py
ansible_autoprovisioner/notifications/slack.py
ansible_autoprovisioner/notifications/telegram.py
ansible_autoprovisioner/tests/test_config.py
ansible_autoprovisioner/tests/test_matching.py
ansible_autoprovisioner/tests/test_state.py
ansible_autoprovisioner/utils/api.py
ansible_autoprovisioner/utils/cli.py
ansible_autoprovisioner/utils/logging.py
ansible_autoprovisioner/utils/ui.py
ansible_autoprovisioner-0.3.0.dist-info/licenses/LICENSE
ansible_autoprovisioner-0.3.0.dist-info/METADATA
ansible_autoprovisioner-0.3.0.dist-info/WHEEL
ansible_autoprovisioner-0.3.0.dist-info/entry_points.txt
ansible_autoprovisioner-0.3.0.dist-info/top_level.txt
ansible_autoprovisioner-0.3.0.dist-info/RECORD
