Metadata-Version: 2.4
Name: ansible-autoprovisioner
Version: 0.3.0
Summary: Automatic Ansible provisioning daemon
Author: Nazar Senchuk
License-Expression: MIT
Classifier: Programming Language :: Python :: 3
Classifier: Operating System :: OS Independent
Requires-Python: >=3.9
License-File: LICENSE
Requires-Dist: ansible>=8.7.0
Requires-Dist: PyYAML
Requires-Dist: requests
Dynamic: license-file
